quantbox/__init__.py
quantbox/cli.py
quantbox/cli_async.py
quantbox/logger.py
quantbox/shell.py
quantbox/shell_async.py
quantbox/user_config.py
quantbox/validators.py
quantbox/adapters/__init__.py
quantbox/adapters/base.py
quantbox/adapters/formatters.py
quantbox/adapters/gm_adapter.py
quantbox/adapters/local_adapter.py
quantbox/adapters/ts_adapter.py
quantbox/adapters/asynchronous/__init__.py
quantbox/adapters/asynchronous/base.py
quantbox/adapters/asynchronous/gm_adapter.py
quantbox/adapters/asynchronous/local_adapter.py
quantbox/adapters/asynchronous/ts_adapter.py
quantbox/adapters/asynchronous/utils.py
quantbox/config/__init__.py
quantbox/config/config_loader.py
quantbox/config/exchanges.toml
quantbox/config/fees_margin.toml
quantbox/config/instruments.toml
quantbox/config/trading_hours.toml
quantbox/config/templates/config.toml
quantbox/gui/__init__.py
quantbox/gui/main_window.py
quantbox/services/__init__.py
quantbox/services/async_data_saver_service.py
quantbox/services/async_market_data_service.py
quantbox/services/data_saver_service.py
quantbox/services/market_data_service.py
quantbox/util/cache_warmup.py
quantbox/util/contract_exchange_mapping.toml
quantbox/util/contract_utils.py
quantbox/util/date_utils.py
quantbox/util/exchange_utils.py
quantbox/util/tools.py
quantbox_cn-0.2.0.dist-info/METADATA
quantbox_cn-0.2.0.dist-info/WHEEL
quantbox_cn-0.2.0.dist-info/entry_points.txt
quantbox_cn-0.2.0.dist-info/licenses/LICENSE
quantbox_cn-0.2.0.dist-info/RECORD
