Metadata-Version: 2.4
Name: quantbox-cn
Version: 0.2.0
Summary: A quantitative trading toolbox with multiple data source support
Author-email: HuChen <curiousbull@outlook.com>
License-File: LICENSE
Classifier: Development Status :: 3 - Alpha
Classifier: Intended Audience :: Financial and Insurance Industry
Classifier: Programming Language :: Python :: 3
Classifier: Programming Language :: Python :: 3.12
Classifier: Topic :: Office/Business :: Financial :: Investment
Requires-Python: >=3.12
Requires-Dist: aiofiles>=23.0.0
Requires-Dist: aiohttp>=3.9.0
Requires-Dist: aiometer>=0.4.0
Requires-Dist: click>=8.0.0
Requires-Dist: motor>=3.3.0
Requires-Dist: numpy>=1.24.0
Requires-Dist: pandas<3.0,>=2.0
Requires-Dist: pymongo<5.0,>=4.0
Requires-Dist: toml>=0.10.0
Requires-Dist: tqdm>=4.65.0
Requires-Dist: tushare>=1.4.0
Provides-Extra: all
Requires-Dist: black>=24.0.0; extra == 'all'
Requires-Dist: gm>=3.0.0; extra == 'all'
Requires-Dist: mypy>=1.8.0; extra == 'all'
Requires-Dist: pyqt6>=6.0.0; extra == 'all'
Requires-Dist: pytest-asyncio>=0.23.0; extra == 'all'
Requires-Dist: pytest-cov>=4.0.0; extra == 'all'
Requires-Dist: pytest>=8.0.0; extra == 'all'
Requires-Dist: ruff>=0.1.0; extra == 'all'
Provides-Extra: build
Requires-Dist: pyinstaller>=6.0.0; extra == 'build'
Provides-Extra: dev
Requires-Dist: black>=24.0.0; extra == 'dev'
Requires-Dist: mypy>=1.8.0; extra == 'dev'
Requires-Dist: pytest-asyncio>=0.23.0; extra == 'dev'
Requires-Dist: pytest-cov>=4.0.0; extra == 'dev'
Requires-Dist: pytest>=8.0.0; extra == 'dev'
Requires-Dist: ruff>=0.1.0; extra == 'dev'
Provides-Extra: goldminer
Requires-Dist: gm>=3.0.0; extra == 'goldminer'
Provides-Extra: gui
Requires-Dist: pyqt6>=6.0.0; extra == 'gui'
